async_packet_test/context.py
async_packet_test/packets.py
async_packet_test/predicates.py
async_packet_test/sniff_future.py
async_packet_test-1.0.0.dist-info/LICENSE
async_packet_test-1.0.0.dist-info/WHEEL
async_packet_test-1.0.0.dist-info/METADATA
async_packet_test-1.0.0.dist-info/RECORD
