Metadata-Version: 2.1
Name: async-packet-test
Version: 1.0.0
Summary: Human readable tests for future expected packets.
Home-page: https://committhis.github.io/async-packet-test/
License: GPL-2.0-only
Author: CommitThis
Author-email: gdavey@committhis.co.uk
Requires-Python: >=3.6,<4.0
Classifier: Framework :: Pytest
Classifier: License :: OSI Approved :: GNU General Public License v2 (GPLv2)
Classifier: Programming Language :: Python :: 3
Classifier: Programming Language :: Python :: 3.10
Classifier: Programming Language :: Python :: 3.6
Classifier: Programming Language :: Python :: 3.7
Classifier: Programming Language :: Python :: 3.8
Classifier: Programming Language :: Python :: 3.9
Classifier: Topic :: Software Development :: Libraries :: Python Modules
Classifier: Topic :: Software Development :: Testing
Classifier: Topic :: System :: Networking
Requires-Dist: scapy (>=2.4,<3.0)
Project-URL: Documentation, https://committhis.github.io/async-packet-test/
Project-URL: Repository, https://github.com/CommitThis/async-packet-test
